{
  "panels": {
    "toolbar": {
      "title": "Model Viewer",
      "x": 6,
      "y": 8,
      "width": 487,
      "height": 127
    },
    "viewport": {
      "title": "Viewport",
      "x": 5,
      "y": 140,
      "width": 343,
      "height": 217
    },
    "modelInfo": {
      "title": "Model Info",
      "x": 5,
      "y": 361,
      "width": 344,
      "height": 448
    },
    "meshParts": {
      "title": "Mesh Parts",
      "x": 9,
      "y": 814,
      "width": 341,
      "height": 455
    },
    "materials": {
      "title": "Materials",
      "x": 1600,
      "y": 7,
      "width": 318,
      "height": 655
    },
    "textureChannels": {
      "title": "Texture Channels",
      "x": 1597,
      "y": 666,
      "width": 320,
      "height": 599
    },
    "loading": {
      "title": "Loading",
      "x": 720,
      "y": 320,
      "width": 320,
      "height": 120
    },
    "runtimeLogs": {
      "title": "Runtime Logs",
      "x": 354,
      "y": 1013,
      "width": 1240,
      "height": 259
    }
  }
}
